{
    "Businesses": [
    {
        "name": "0500 MECHANICS",
        "phone":"(208) 356-0500",
        "website": "www.0500mechanics.com",
        "image": "image1.jpg"
    },

    {
        "name": "0500 MECHANICS",
        "phone":"(208) 356-0500",
        "website": "www.0500mechanics.com",
        "image": "image1.jpg" 
    },
    {
        "name": "0500 MECHANICS",
        "phone":"(208) 356-0500",
        "website": "www.0500mechanics.com",
        "image": "image1.jpg" 
    },

    {
        "name": "0500 MECHANICS",
        "phone":"(208) 356-0500",
        "website": "www.0500mechanics.com",
        "image": "image1.jpg" 
    },

    {
        "name": "0500 MECHANICS",
        "phone":"(208) 356-0500",
        "website": "www.0500mechanics.com",
        "image": "image1.jpg" 
    },

    {
        "name": "0500 MECHANICS",
        "phone":"(208) 356-0500",
        "website": "www.0500mechanics.com",
        "image": "image1.jpg" 
    },

    {
        "name": "0500 MECHANICS",
        "phone":"(208) 356-0500",
        "website": "www.0500mechanics.com",
        "image": "image1.jpg" 
    },

    {
        "name": "0500 MECHANICS",
        "phone":"(208) 356-0500",
        "website": "www.0500mechanics.com",
        "image": "image1.jpg" 
    },

    {
        "name": "0500 MECHANICS",
        "phone":"(208) 356-0500",
        "website": "www.0500mechanics.com",
        "image": "image1.jpg" 
    },

    {
        "name": "0500 MECHANICS",
        "phone":"(208) 356-0500",
        "website": "www.0500mechanics.com",
        "image": "image1.jpg" 
    }
    ]
}